blog/__init__.py
blog/admin.py
blog/adminforms.py
blog/apis.py
blog/apps.py
blog/models.py
blog/serializers.py
blog/tests.py
blog/urls.py
blog/views.py
blog/middleware/__init__.py
blog/middleware/user_id.py
blog/migrations/0001_initial.py
blog/migrations/0002_post_content_html.py
blog/migrations/__init__.py
comment/__init__.py
comment/admin.py
comment/apps.py
comment/forms.py
comment/models.py
comment/tests.py
comment/urls.py
comment/views.py
comment/migrations/0001_initial.py
comment/migrations/0002_auto_20220925_1216.py
comment/migrations/__init__.py
comment/templatetags/__init__.py
comment/templatetags/comment_block.py
config/__init__.py
config/admin.py
config/apps.py
config/models.py
config/tests.py
config/urls.py
config/views.py
config/migrations/0001_initial.py
config/migrations/__init__.py
typeidea/__init__.py
typeidea/autocomplete.py
typeidea/base_admin.py
typeidea/custom_site.py
typeidea/urls.py
typeidea/wsgi.py
typeidea/settings/__init__.py
typeidea/settings/base.py
typeidea/settings/develop.py
typeidea/settings/product.py
typeidea_wuxin-1.0.data/scripts/manage.py
typeidea_wuxin-1.0.data/scripts/wsgi.py
typeidea_wuxin-1.0.dist-info/METADATA
typeidea_wuxin-1.0.dist-info/WHEEL
typeidea_wuxin-1.0.dist-info/entry_points.txt
typeidea_wuxin-1.0.dist-info/top_level.txt
typeidea_wuxin-1.0.dist-info/RECORD
