Metadata-Version: 2.1
Name: typeidea-wuxin
Version: 1.0
Summary: Blog System base on Django
Home-page: https://www.the5fire.com
Author: the5fire
Author-email: thefivefire@gmail.com
License: MIT
Platform: UNKNOWN
Classifier: Development Status :: 3 - Alpha
Classifier: Intended Audience :: Developers
Classifier: Topic :: Software Development :: Libraries
Classifier: License :: OSI Approved :: MIT License
Classifier: Programming Language :: Python :: 3.6
Requires-Dist: django (~=2.2)
Requires-Dist: gunicorn (==19.8.1)
Requires-Dist: supervisor (==4.0.0dev0)
Requires-Dist: xadmin (==0.6.1)
Requires-Dist: mysqlclient (==1.3.12)
Requires-Dist: django-ckeditor (==5.4.0)
Requires-Dist: django-rest-framework (==0.1.0)
Requires-Dist: django-redis (==4.8.0)
Requires-Dist: django-autocomplete-light (==3.2.10)
Requires-Dist: mistune (==0.8.3)
Requires-Dist: Pillow (==4.3.0)
Requires-Dist: coreapi (==2.3.3)
Requires-Dist: hiredis (==0.2.0)
Requires-Dist: django-debug-toolbar (==1.9.1)
Requires-Dist: django-silk (==2.0.0)
